[{"Similarity":"0.975","Title":"Categorial compositionality continued (further) A category theory explanation for the systematicity of recursive cognitive capacities","Year":2012},{"Similarity":"0.961","Title":"Episode Blending as Result of Analogical Problem Solving","Year":2001},{"Similarity":"0.958","Title":"Conceptual Combination as Theory Formation","Year":2001},{"Similarity":"0.957","Title":"Similarity-Based Qualitative Simulation","Year":2005},{"Similarity":"0.956","Title":"Analogy and Transfer Encoding the Problem at the Right Level of Abstraction","Year":2005},{"Similarity":"0.954","Title":"A Fundamental Limitation of Symbol-Argument-Argument Notation As a Model of Human Relational Representations","Year":2004}]