[{"Similarity":"0.915","Title":"The Importance of Long-term Memory in Infant Perceptual Categorization","Year":2003},{"Similarity":"0.908","Title":"The Importance of Starting Blurry Simulating Improved Basic-Level Category Learning in Infants Due to Weak Visual Acuity","Year":2002},{"Similarity":"0.876","Title":"The Emergence of Words","Year":2001},{"Similarity":"0.876","Title":"Learning to Associate Object Categories and Label Categories A Self-Organising Model","Year":2008},{"Similarity":"0.871","Title":"A neuroplausible computational model of vision also exhibits asymmetry in developmental category learning","Year":2011},{"Similarity":"0.87","Title":"The Impact of Labels on Visual Categorisation a Neural Network Model","Year":2008}]