[{"Similarity":"0.958","Title":"Calculating Probabilities Simplifies Word Learning","Year":2017},{"Similarity":"0.916","Title":"Categorical Recurrence Analysis of Child Language","Year":2005},{"Similarity":"0.911","Title":"Characterizing Motherese On the Computational Structure of Child-Directed Language","Year":2007},{"Similarity":"0.907","Title":"Modeling the Development of Determiner Productivity in Childrens Early Speech","Year":2013},{"Similarity":"0.904","Title":"Assessing the Efficacy of Transitional Probabilities for Learning Syntactic Categories","Year":2007},{"Similarity":"0.901","Title":"Dynamical systems modeling of the child--mother dyad Causality between child-directed language complexity and language development","Year":2016}]