[{"Similarity":"0.974","Title":"Observed motor actions affect valence judgments","Year":2014},{"Similarity":"0.974","Title":"Cognitive Representations and Enacting Actions in Computer Simulated Environments","Year":2011},{"Similarity":"0.957","Title":"Turn, Turn, Turn: Perceiving Global and Local, Clockwise and Counterclockwise Rotations","Year":2015},{"Similarity":"0.957","Title":"Turn Turn Turn Perceiving Global and Local Clockwise and Counterclockwise Rotations","Year":2015},{"Similarity":"0.944","Title":"Behavioral Dynamics of a Collision Avoidance Task: How Asymmetry Stabilizes Performance","Year":2015},{"Similarity":"0.944","Title":"Behavioral Dynamics of a Collision Avoidance Task How Asymmetry Stabilizes Performance","Year":2015}]