[{"Similarity":"0.894","Title":"Infants Use Social Signals to Learn from Unfamiliar Referential Cues","Year":2011},{"Similarity":"0.886","Title":"What You Learn Is What You See Using Eye Movements to Study Infant Cross-Situational Word Learning","Year":2008},{"Similarity":"0.884","Title":"Mechanisms Underlying the Effects of Labels on Cognitive Development","Year":2005},{"Similarity":"0.873","Title":"Social Cues Support Learning about Objects from Statistics in Infancy","Year":2010},{"Similarity":"0.87","Title":"The Effect of Labels on Visual Attention An Eye Tracking Study","Year":2010},{"Similarity":"0.869","Title":"Cued Attention and Learning of Spatial Context in Children","Year":2011}]