[{"Similarity":"0.889","Title":"The Adaptability of Language Specific Verb Lexicalization Biases","Year":2004},{"Similarity":"0.884","Title":"Linguistic input overrides conceptual biases When goals dont matter","Year":2015},{"Similarity":"0.884","Title":"Linguistic input overrides conceptual biases: When goals don't matter","Year":2015},{"Similarity":"0.881","Title":"Language acquisition in Down Syndrome from embodied perspective How body constrains language acquisition","Year":2012},{"Similarity":"0.866","Title":"Fast-Mapping and Reorganization Development of Verb Meanings as a System","Year":2008},{"Similarity":"0.851","Title":"Point-Light Displays Illuminate the Abstract Nature of Childrens Motion Verb Representations","Year":2000}]