[{"Similarity":"0.953","Title":"More than Words The Many Ways Extended Discourse Facilitates Word Learning","Year":2016},{"Similarity":"0.944","Title":"Online Processing of Speech and Social Information in Early Word Learning","Year":2013},{"Similarity":"0.939","Title":"Childrens Use of Disfluencies for Pragmatic Inference in Lexical Development","Year":2009},{"Similarity":"0.934","Title":"Early Colour Word Learning in British Infants","Year":2017},{"Similarity":"0.929","Title":"Beyond Naive Cue Combination Salience and Social Cues in Early Word Learning","Year":2014},{"Similarity":"0.912","Title":"The development of predictive processes in childrens discourse understanding","Year":2013}]