[{"Similarity":"0.978","Title":"Individual Differences in Chunking Ability Predict On-line Sentence Processing","Year":2015},{"Similarity":"0.934","Title":"Syntax in music and language The role of cognitive control","Year":2013},{"Similarity":"0.893","Title":"When More in Statistical Learning Means Less in Language Individual Differences in Predictive Processing of Adjacent Dependencies","Year":2010},{"Similarity":"0.892","Title":"A Temporal Signal Reveals Chunk Structure in the Writing of Word Phrases","Year":2006},{"Similarity":"0.891","Title":"Zen in the Art of Language Acquisition Statistical Learning and the Less is More Hypothesis","Year":2000},{"Similarity":"0.887","Title":"Extending Statistical Learning Farther and Further Long-Distance Dependencies and Individual Differences in Statistical Learning and Language","Year":2007}]