[{"Similarity":"0.989","Title":"Structure and Application of Dynamical Models in Cognitive Science","Year":2014},{"Similarity":"0.975","Title":"Embodied anticipation for swift re-adaptation in neurocomputational cognitive architectures for robotic agents","Year":2009},{"Similarity":"0.962","Title":"The Concept of Simulation in Control-Theoretic Accounts of Motor Control and Action Perception","Year":2008},{"Similarity":"0.956","Title":"Integrating Cognitive Architectures with External Environments Approaches and Contributions to Validation","Year":2008},{"Similarity":"0.952","Title":"From Reduction Back to Higher Levels","Year":2008},{"Similarity":"0.948","Title":"A Constructivist Model of Robot Perception and Performance","Year":2000}]