[{"Similarity":"0.955","Title":"Interactive Models of Collaborative Communication","Year":2001},{"Similarity":"0.944","Title":"On the automaticity of reduction in dialogue Cognitive load and repeated multimodal references","Year":2014},{"Similarity":"0.944","Title":"Communicative Gestures and Memory Load","Year":2009},{"Similarity":"0.942","Title":"The Role of Gesture in Second Language Learning Communication Acquisition  Retention","Year":2012},{"Similarity":"0.942","Title":"Information theoretic factors in marking linguistic focus A laboratory-language approach","Year":2017},{"Similarity":"0.941","Title":"Beat gestures facilitate speech production","Year":2014}]