[{"Similarity":"0.913","Title":"The Influence of Collective Opinion on True-False Judgment and Information-Sharing Decision","Year":2013},{"Similarity":"0.907","Title":"Reasoning ability predicts irrational worldview but not conspiracy belief","Year":2017},{"Similarity":"0.905","Title":"Lasting Political Attitude Change Induced by False Feedback About Own Survey Responses","Year":2016},{"Similarity":"0.904","Title":"Construal level affects intuitive moral responses to narrative content","Year":2016},{"Similarity":"0.903","Title":"Effects of information comprehensibility and argument type on lay recipients readiness to defer to experts when deciding about scientific knowledge claims","Year":2011},{"Similarity":"0.901","Title":"Is it fair Textual effects on the salience of moral foundations","Year":2017}]