[{"Similarity":"0.948","Title":"Categorisation Deference and Cognitive Style","Year":2010},{"Similarity":"0.94","Title":"Deference and Essentialism in the Categorization of Chemical Kinds","Year":2003},{"Similarity":"0.915","Title":"Some New Evidence for Concept Stability","Year":2003},{"Similarity":"0.9","Title":"Translating From Perceptual to Cognitive Coding","Year":2007},{"Similarity":"0.891","Title":"Intentional and Incidental Classification Learning in Category Use","Year":2006},{"Similarity":"0.888","Title":"Similarity and Categorisation Getting Dissociations in Perspective","Year":2004}]