[{"Similarity":"0.975","Title":"Social Science Complex Cognition in Early AIDS Research","Year":2008},{"Similarity":"0.956","Title":"Stepping Up to the Blackboard: Distributed Cognition in Doctor-Patient Interactions","Year":2015},{"Similarity":"0.956","Title":"Stepping Up to the Blackboard Distributed Cognition in Doctor-Patient Interactions","Year":2015},{"Similarity":"0.948","Title":"Changing Global Warming Beliefs with Scientific Information Knowledge Attitudes and RTMD (Reinforced Theistic Manifest Destiny Theory)","Year":2012},{"Similarity":"0.945","Title":"The Permeability of Fictional Worlds","Year":2016},{"Similarity":"0.941","Title":"Which Parts of Scientific Explanations are Most Important","Year":2011}]