[{"Similarity":"0.977","Title":"Does Mandarin Spatial Metaphor for Time Influence Chinese Deaf Signers Spatio-Temporal Reasoning","Year":2017},{"Similarity":"0.957","Title":"Motor Simulation and Verbal Association in Idiom-Idiom Verification Effects of Imageability","Year":2011},{"Similarity":"0.953","Title":"Do English and Mandarin Speakers Think Differently About Time","Year":2008},{"Similarity":"0.923","Title":"Is Time Going to Stand Hebrew and English Speakers Conceptions of Time","Year":2006},{"Similarity":"0.905","Title":"Which is in front of Chinese people Past or Future A study on Chinese peoples space-time mapping","Year":2016},{"Similarity":"0.889","Title":"Priming Spatial Perspective","Year":2011}]