[{"Similarity":"0.998","Title":"Conceptual Combination versus Critical CombinationDevising Creative Solutions using the Sequential Application of Crowds","Year":2011},{"Similarity":"0.998","Title":"The Effects of Criticism on Creative Ideation","Year":2015},{"Similarity":"0.996","Title":"Experimental investigation of effects of representations and contexts on comprehension and generation of line graphs","Year":2011},{"Similarity":"0.996","Title":"Text Coherence and Judgments of Essay Quality Models of Quality and Coherence","Year":2011},{"Similarity":"0.995","Title":"Social Roles and Category Use A Study of Creativity Assessment","Year":2013},{"Similarity":"0.995","Title":"Cohesion Coherence and Expert Evaluations of Writing Proficiency","Year":2010}]