[{"Similarity":"0.924","Title":"Gesture and Language Production in Communication through Bar Graphs","Year":2013},{"Similarity":"0.914","Title":"What can Hand Movements Tell us about Audience Engagement","Year":2017},{"Similarity":"0.897","Title":"Establish Trust and Express Attitude for a Non-Humanoid Robot","Year":2016},{"Similarity":"0.892","Title":"Examining Multiscale Movement Coordination in Collaborative Problem Solving","Year":2017},{"Similarity":"0.888","Title":"The Effects of Communication Medium Upon Collaborative Orientation Task Performance","Year":2010},{"Similarity":"0.885","Title":"Cognitive processes of artistic creation A field study of a traditional Chinese ink painters drawing process","Year":2004}]