[{"Similarity":"0.916","Title":"Effects of Filler-gap Dependencies Working Memory Requirements for Parsing","Year":2011},{"Similarity":"0.915","Title":"Developmentally plausible learning of word categories from distributional statistics","Year":2016},{"Similarity":"0.899","Title":"Case Word Order and Language Learnability Insights from Connectionist Modeling","Year":2002},{"Similarity":"0.899","Title":"The Combinatorial Power of Experience","Year":2016},{"Similarity":"0.895","Title":"Word Embedding Distance Does not Predict Word Reading Time","Year":2017},{"Similarity":"0.893","Title":"Subject Omission in Childrens Language The Case for Performance Limitations in Learning","Year":2002}]