[{"Similarity":"0.99","Title":"Causal Reasoning in Infants and Adults Revisiting backwards-blocking","Year":2016},{"Similarity":"0.986","Title":"Causal determinism in toddlers","Year":2013},{"Similarity":"0.98","Title":"Sensitivity to Confounding in Causal Inference From Childhood to Adulthood","Year":2004},{"Similarity":"0.975","Title":"Do Preschoolers Understand Causality A Critical Look","Year":2005},{"Similarity":"0.975","Title":"Toddlers understanding of prediction intervention and means of transmission When psychological outcomes are easier than physical ones","Year":2011},{"Similarity":"0.975","Title":"Causal Determinism and Preschoolers Causal Inferences","Year":2005}]