[{"Similarity":"0.925","Title":"Individuals process of metaphor interpretations and interestingness cognition","Year":2012},{"Similarity":"0.924","Title":"Embodied Synchrony of Nonverbal Behaviour in Counseling a Case Study of Role Playing School Counseling","Year":2006},{"Similarity":"0.916","Title":"A Written Version of Sign Language can Enhance Signing Deaf Individuals Comprehension and Learning from Texts","Year":2013},{"Similarity":"0.907","Title":"Gestures in Communication through Line Graphs","Year":2012},{"Similarity":"0.906","Title":"Extended Metaphors are Very Persuasive","Year":2016},{"Similarity":"0.903","Title":"Discourse Acquisition in Pear Stories of Preschool-aged Children","Year":2017}]