[{"Similarity":"0.962","Title":"New Frameworks of Rationality","Year":2013},{"Similarity":"0.945","Title":"The Representation of Judgment Heuristics and the Generality Problem","Year":2007},{"Similarity":"0.918","Title":"Inference of Intention and Permissibility in Moral Decision Making","Year":2015},{"Similarity":"0.907","Title":"Framing Effects and Modal Illusions How to Characterize Framing Effects as an Intensional Phenomenon","Year":2005},{"Similarity":"0.874","Title":"Intentionality and choice","Year":2013},{"Similarity":"0.874","Title":"The nave utility calculus Joint inferences about the costs and rewards of actions","Year":2015}]