[{"Similarity":"0.969","Title":"The Roles of Knowledge and Memory in Generating Top-10 Lists","Year":2015},{"Similarity":"0.911","Title":"Worm holes in memory Is memory one representation or many","Year":2013},{"Similarity":"0.909","Title":"Encoding and Retrieval Efficiency of Episodic Data in a Modified Sparse Distributed Memory System","Year":2005},{"Similarity":"0.894","Title":"Modeling Opportunistic Strategy for Information Navigation","Year":2001},{"Similarity":"0.88","Title":"Exploring Decision Rules and Sampling Dynamics in Recognition Memory","Year":2012},{"Similarity":"0.879","Title":"Linking Memory Models and Decision Models Insights on Frequency and SpeedAccuracy Trade-off","Year":2014}]