[{"Similarity":"0.881","Title":"Body Parts and the First 100 Verbs","Year":2006},{"Similarity":"0.874","Title":"Point-Light Displays Illuminate the Abstract Nature of Childrens Motion Verb Representations","Year":2000},{"Similarity":"0.843","Title":"Paw Preference Correlates to Task Performance in Dogs","Year":2005},{"Similarity":"0.841","Title":"Social Cues Affect Grasping Hysteresis in ASD","Year":2015},{"Similarity":"0.837","Title":"Deconstructing tomorrow How children learn the semantics of time","Year":2016},{"Similarity":"0.837","Title":"Sound Symbolism and Early Word Learning in Two Languages","Year":2003}]