[{"Similarity":"0.912","Title":"Modeling the Logarithmic-To-Linear Shift In Representations Of Numerical Magnitudes","Year":2011},{"Similarity":"0.904","Title":"Placeholder structure and numerical computation","Year":2011},{"Similarity":"0.899","Title":"The Effect of Physical Load in Cognitive Process of Estimation","Year":2013},{"Similarity":"0.896","Title":"Development of Numerosity Estimation  A Linear to Logarithmic Shift","Year":2015},{"Similarity":"0.896","Title":"Development of Numerosity Estimation:  A Linear to Logarithmic Shift?","Year":2015},{"Similarity":"0.895","Title":"Probing the mental number line A between-task analysis of spatial-numerical associations","Year":2015}]