[{"Similarity":"0.99","Title":"The Statistical Brain Reply to Marcus The Algebraic Mind","Year":2003},{"Similarity":"0.974","Title":"Hyperintentionality in schizophrenia An fMRI study","Year":2009},{"Similarity":"0.974","Title":"The Sparsity of Simple Recurrent Networks in Musical Structure Learning","Year":2009},{"Similarity":"0.96","Title":"TRACX2 a RAAM-like autoencoder modeling  graded chunking in infant visual-sequence learning","Year":2017},{"Similarity":"0.96","Title":"Babies Variables and Relational Correlations","Year":2000},{"Similarity":"0.959","Title":"A Connectionist Simulation of Structural Rule Learning in Language Acquisition","Year":2008}]