[{"Similarity":"0.991","Title":"Lateral Inhibition Explains Savings in Conditioning and Extinction","Year":2006},{"Similarity":"0.988","Title":"Preventing Catastrophic Interference in Multiple-Sequence Learning Using Coupled Reverberating Elman Networks","Year":2002},{"Similarity":"0.98","Title":"How many Neurons for your Grandmother  Three Arguments for Localised Representations","Year":2012},{"Similarity":"0.979","Title":"Neural Synchrony Through Controlled Tracking","Year":2001},{"Similarity":"0.976","Title":"Neural Circuits for Any-Time Phrase Recognition with Applications in Cognitive Models and Human-Robot Interaction","Year":2012},{"Similarity":"0.974","Title":"Learning the Structure of Abstract Groups","Year":2009}]