[{"Similarity":"0.988","Title":"Frequency and Contextual Diversity Effects in Cross-Situational Word Learning","Year":2009},{"Similarity":"0.988","Title":"Temporal Contiguity in Cross-Situational Statistical Learning","Year":2009},{"Similarity":"0.987","Title":"Cross-Situational Statistical Learning Implicit or Intentional","Year":2010},{"Similarity":"0.984","Title":"4-month-olds Discover Algebraic Patterns in Music That 75-month-olds Do Not","Year":2006},{"Similarity":"0.979","Title":"The roles of item repetition and position in infant sequence learning","Year":2017},{"Similarity":"0.973","Title":"The Role of Explaining Away in Human Abstract Rule Induction","Year":2010}]