[{"Similarity":"0.927","Title":"Seeing is Believing Priors Trust and Base Rate Neglect","Year":2007},{"Similarity":"0.923","Title":"Reducing overconfidence in forecasting with repeated judgement elicitation","Year":2015},{"Similarity":"0.919","Title":"Avoiding the language-as-a-fixed-effect fallacy How to estimate outcomesof linear mixed models","Year":2014},{"Similarity":"0.919","Title":"Sensitivity to statistical regularities People (largely) follow Benfords law","Year":2009},{"Similarity":"0.918","Title":"Nave Sampling and Format Dependence in Subjective Probability Calibration","Year":2003},{"Similarity":"0.917","Title":"In What Sense is P(AB) P(B)  P(AB) The Relationship between Distributional Format and Subjective Probability Estimates","Year":2010}]