[{"Similarity":"0.961","Title":"Mutual Exclusivity in Cross-Situational Statistical Learning","Year":2008},{"Similarity":"0.957","Title":"Visual Statistical Learning in Infants","Year":2001},{"Similarity":"0.956","Title":"Developmental Differences in Childrens Statistical Learning Abilities","Year":2016},{"Similarity":"0.951","Title":"Neurophysiological Correlates of Visual Statistical Learning in Adults and Children","Year":2011},{"Similarity":"0.944","Title":"Visual abstract rule learning by 3- and 4-month-old infants","Year":2015},{"Similarity":"0.942","Title":"The effect of stimulus familiarity on modality dominance","Year":2004}]