[{"Similarity":"1","Title":"Odor naming is difficult even for wine and coffee experts","Year":2015},{"Similarity":"0.984","Title":"Words and meaning How the lexical encoding of technical concepts contributes to their mental representation","Year":2009},{"Similarity":"0.981","Title":"How Does Information about Creative Process Affect Audience Appreciation of Artwork","Year":2006},{"Similarity":"0.979","Title":"Perception of e-mail personality at zero-acquaintance Extraversion takes care of itself Neuroticism is a worry","Year":2003},{"Similarity":"0.979","Title":"Conceptual Combination versus Critical CombinationDevising Creative Solutions using the Sequential Application of Crowds","Year":2011},{"Similarity":"0.979","Title":"Language does not explain the wine-specific memory advantage of wine experts","Year":2016}]