[{"Similarity":"0.977","Title":"Embodied cognition and passive processing What hand-tracking tells us about syntactic processing in L1 and L2 speakers of English","Year":2015},{"Similarity":"0.977","Title":"Embodied cognition and passive processing: What hand-tracking tells us about syntactic processing in L1 and L2 speakers of English","Year":2015},{"Similarity":"0.975","Title":"The Influence of Conceptual Structure on Structural Priming","Year":2011},{"Similarity":"0.967","Title":"Phrase Structure Priming Across Sentences Facilitation or Reconfiguration","Year":2011},{"Similarity":"0.962","Title":"Space agency and word order Evidence from Greek","Year":2013},{"Similarity":"0.947","Title":"Expectancy for the Morphological Form of Verbs During Semantic Priming","Year":2005}]