[{"Similarity":"0.977","Title":"Facial Motor Information is Sufficient for Identity Recognition","Year":2017},{"Similarity":"0.967","Title":"Modeling the Other-race Advantage with PCA","Year":2005},{"Similarity":"0.958","Title":"A New Angle on the EMPATH Model Spatial Frequency Orientation in Recognition of Facial Expressions","Year":2012},{"Similarity":"0.957","Title":"Predicting Experimental Similarity Ratings and Recognition Rates for Individual Natural Stimuli with the NIM Model","Year":2005},{"Similarity":"0.956","Title":"The face-space duality hypothesis a computational model","Year":2016},{"Similarity":"0.952","Title":"Distinguishing Between Perceptual and Decisional Sources of Holism in Face Processing","Year":2007}]