[{"Similarity":"0.976","Title":"Rapid adaptation in online pragmatic interpretation of contrastive prosody","Year":2014},{"Similarity":"0.973","Title":"Listen, Look, Go! The Role of Prosody and Gaze in Turn-End Anticipation","Year":2015},{"Similarity":"0.973","Title":"Listen Look Go The Role of Prosody and Gaze in Turn-End Anticipation","Year":2015},{"Similarity":"0.971","Title":"Turn-boundary projection Looking ahead","Year":2011},{"Similarity":"0.967","Title":"Looking To Understand The Coupling Between Speakers and Listeners Eye Movements and its Relationship to Discourse Comprehension","Year":2004},{"Similarity":"0.966","Title":"Incremental Referential Domain Circumscription during Processing of Natural and Synthesized Speech","Year":2002}]