[{"Similarity":"0.99","Title":"How Reading Goals and Rhetorical Signals Influence Recipients Recognition of Intertextual Conflicts","Year":2011},{"Similarity":"0.988","Title":"Effects of Writing on Conceptual Coherence","Year":2006},{"Similarity":"0.986","Title":"The Effects of Criticism on Creative Ideation","Year":2015},{"Similarity":"0.984","Title":"How Does Information about Creative Process Affect Audience Appreciation of Artwork","Year":2006},{"Similarity":"0.984","Title":"Online Discussion Processes Effects of the Previous Messages Evaluations Knowledge Content Social Cues and Personal Information on the Current Message","Year":2007},{"Similarity":"0.982","Title":"Using the Social of Tagging The Interplay of Social Tags and the Strength of Association in Navigation and Learning Processes","Year":2010}]