[{"Similarity":"0.937","Title":"Convention-formation in iterated reference games","Year":2017},{"Similarity":"0.929","Title":"Biases and labeling in iterative pragmatic reasoning","Year":2017},{"Similarity":"0.921","Title":"Modeling transfer of high-order uncertain information","Year":2017},{"Similarity":"0.912","Title":"Predicative Metaphors Are Understood as Two-Stage Categorization Computational Evidence by Latent Semantic Analysis","Year":2007},{"Similarity":"0.909","Title":"Learning biases may prevent lexicalization of pragmatic inferences a case study combining iterated (Bayesian) learning and functional selection","Year":2016},{"Similarity":"0.902","Title":"Extremely costly intensifiers are stronger than quite costly ones","Year":2015}]