[{"Similarity":"0.899","Title":"Integrating Distributional Prosodic and Phonological Information in a Connectionist Model of Language Acquisition","Year":2001},{"Similarity":"0.869","Title":"Colorless Green Ideas Sleep Furiously Revisited A Statistical Perspective","Year":2005},{"Similarity":"0.851","Title":"A Model of Infant Learning of Word Stress","Year":2005},{"Similarity":"0.845","Title":"Phonological and Distributional Cues in Syntax Acquisition Scaling up the Connectionist Approach to Multiple-Cue Integration","Year":2003},{"Similarity":"0.843","Title":"Subjacency Constraints without Universal Grammar Evidence from Artificial Language Learning and Connectionist Modeling","Year":2000},{"Similarity":"0.839","Title":"Generalization in a Model of Infant Sensitivity to Syntactic Variation","Year":2005}]