[{"Similarity":"0.96","Title":"Childrens Use of Disfluencies for Pragmatic Inference in Lexical Development","Year":2009},{"Similarity":"0.943","Title":"Are children flexible speakers  Effects of typicality and listener needs in childrens event descriptions","Year":2016},{"Similarity":"0.941","Title":"More than Words The Many Ways Extended Discourse Facilitates Word Learning","Year":2016},{"Similarity":"0.927","Title":"Contextual inferences over speakers pragmatic intentions Preschoolers comprehension of contrastive prosody","Year":2013},{"Similarity":"0.918","Title":"Sources of developmental change in pragmatic inferences about scalar terms","Year":2015},{"Similarity":"0.912","Title":"Childrens Online Processing of Ad-Hoc Implicatures","Year":2015}]