[{"Similarity":"0.919","Title":"Why we Should Not Forget About the Non-social World Subjective Preferences Exploratory Eye-movements and Individual Differences","Year":2013},{"Similarity":"0.9","Title":"Does Attention Confer Importance Examining Evidence from the Multiattribute Choice Domain","Year":2011},{"Similarity":"0.895","Title":"Decoupling of Intuitions and Performance in the Use of Complex Visual Displays","Year":2008},{"Similarity":"0.875","Title":"The role of presentation order and orientation on information search and evaluations An eye-tracking study","Year":2017},{"Similarity":"0.859","Title":"The Role of Visual Coherence in Graphical Passwords","Year":2013},{"Similarity":"0.858","Title":"Processing and Integrating Multimodal Material  The Influence of Color-Coding","Year":2005}]