[{"Similarity":"0.958","Title":"The Disproportionate Face Inversion Effect in Recognition Memory","Year":2010},{"Similarity":"0.946","Title":"State-Trace Analysis of the Face Inversion Effect","Year":2009},{"Similarity":"0.944","Title":"Neural Correlates of Episodic Memory Formation in Audio-Visual Pairing Tasks","Year":2012},{"Similarity":"0.924","Title":"Mind-wandering with and without Awareness An fMRI study of spontaneous thought processes","Year":2006},{"Similarity":"0.922","Title":"An examination of the ERP correlates of recognition memory using state-trace analysis","Year":2010},{"Similarity":"0.921","Title":"Different Strategies in Solving Series Completion Inductive Reasoning Problems An fMRI and Computational Study","Year":2013}]