[{"Similarity":"0.954","Title":"Using Concept Map to Evaluate Learning by Searching","Year":2012},{"Similarity":"0.93","Title":"Reasoning with Internal and External Representations A Case Study with Expert Architects","Year":2006},{"Similarity":"0.928","Title":"Applying Text Comprehension and Active Reading Principles to Adaptive Hyperbooks","Year":2003},{"Similarity":"0.928","Title":"Constructive Perception A Metacognitive Skill for Coordinating Perception and Conception","Year":2003},{"Similarity":"0.927","Title":"A Graph-Oriented Approach to Measuring Expertise- Detecting Structural Differences between Experts and Intermediates","Year":2012},{"Similarity":"0.927","Title":"As Useful as a Bicycle to a Fish Exploration versus Constraint in Creativity","Year":2006}]