[{"Similarity":"0.992","Title":"The influence of structural salience and verbalisation on finding the return path","Year":2014},{"Similarity":"0.991","Title":"Spatial cognition the return path","Year":2013},{"Similarity":"0.99","Title":"Lets Go for a Run Planning Routes to Remember","Year":2011},{"Similarity":"0.99","Title":"Effects of Complementary Control on the Coordination Dynamics of Joint-Action","Year":2015},{"Similarity":"0.99","Title":"SQUARELAND 20 A flexible and realistic virtual environment for investigating cognitive processes in human wayfinding","Year":2014},{"Similarity":"0.987","Title":"Investigating Strategy Discovery and Coordination in a Novel Virtual Sheep Herding Game among Dyads","Year":2015}]