[{"Similarity":"0.986","Title":"Early and Late Effects of Morphological Decomposition Brain Correlates of Family Size Effects on Complex Words and Pseudowords","Year":2009},{"Similarity":"0.98","Title":"The Influence of Writing Experiences on Holistic Processing in Chinese Character Recognition","Year":2011},{"Similarity":"0.98","Title":"Voices and Variants Effects of Voice on the Form-Based Processing of Words with Different Phonological Variants","Year":2014},{"Similarity":"0.977","Title":"Effects of Near and Distant Phonological Neighbors on Picture Naming","Year":2010},{"Similarity":"0.976","Title":"Does Gender Information Influence Early Phases of Spoken Word Recognition","Year":2005},{"Similarity":"0.976","Title":"What Happens When Experts Over- or Underestimate a Laypersons Knowledge in Communication Effects on Learning and Question Asking","Year":2005}]