[{"Similarity":"0.988","Title":"Ethical System Formalization using Non-Monotonic Logics","Year":2007},{"Similarity":"0.978","Title":"Apparent Paradoxes in Moral Reasoning Or how you forced him to do it even though he wasnt forced to do it","Year":2011},{"Similarity":"0.977","Title":"Knowledge and Luck","Year":2014},{"Similarity":"0.976","Title":"Intentionality and choice","Year":2013},{"Similarity":"0.974","Title":"Counterfactual Reasoning How to Organize a Possible World","Year":2003},{"Similarity":"0.974","Title":"A non-monotonic extension of universal moral grammar theory","Year":2015}]