[{"Similarity":"0.97","Title":"Establish Trust and Express Attitude for a Non-Humanoid Robot","Year":2016},{"Similarity":"0.955","Title":"Examining Multiscale Movement Coordination in Collaborative Problem Solving","Year":2017},{"Similarity":"0.936","Title":"Physiological entrainment and behavioral coordination in a collective creative construction task","Year":2015},{"Similarity":"0.936","Title":"Physiological entrainment and behavioral coordination in a collective, creative construction task","Year":2015},{"Similarity":"0.917","Title":"Investigation on Using 3D Printed Liver during Surgery","Year":2015},{"Similarity":"0.914","Title":"Embodied Synchrony of Nonverbal Behaviour in Counseling a Case Study of Role Playing School Counseling","Year":2006}]