[{"Similarity":"0.933","Title":"Seeing is Believing Priors Trust and Base Rate Neglect","Year":2007},{"Similarity":"0.923","Title":"The Role of Vagueness in the Numerical Translation of Verbal Probabilities A Fuzzy Approach","Year":2010},{"Similarity":"0.913","Title":"Belief Clustering in Inferences about Correlation","Year":2009},{"Similarity":"0.913","Title":"Confirmation bias is rational when hypotheses are sparse","Year":2009},{"Similarity":"0.903","Title":"A toolbox of methods for probabilistic inference","Year":2017},{"Similarity":"0.902","Title":"Vector Space Semantic Models  Predict Subjective Probability Judgments for Real-World Events","Year":2016}]