[{"Similarity":"0.934","Title":"The Activation of Hypotheses during Abductive Reasoning","Year":2007},{"Similarity":"0.926","Title":"Uncertainty and dependency in causal inference","Year":2011},{"Similarity":"0.92","Title":"The Redundancy Effect in Human Causal Learning Evidence Against a Comparator Theory Explanation","Year":2017},{"Similarity":"0.907","Title":"High-Level Cognitive Processes in Causal Judgments An Integrated Model","Year":2004},{"Similarity":"0.888","Title":"A Causal Power Approach to Learning with Rates","Year":2006},{"Similarity":"0.887","Title":"Rational Assessments of Covariation and Causality","Year":2000}]